CalibDBReader/__init__.py
CalibDBReader/cdbr.py
calibdbreader-0.6.0.dist-info/licenses/LICENSE
calibdbreader-0.6.0.dist-info/METADATA
calibdbreader-0.6.0.dist-info/WHEEL
calibdbreader-0.6.0.dist-info/top_level.txt
calibdbreader-0.6.0.dist-info/RECORD
