Metadata-Version: 2.4
Name: CalibDBReader
Version: 0.6.0
Summary: Reader for the calibration database
Author-email: Romolo Politi <Romolo.Politi@inaf.it>
License: GNU GPL ver3
Project-URL: Repository, https://github.com/RomoloPoliti-INAF/Calib_DB_Reader
Project-URL: Changelog, https://github.com/RomoloPoliti-INAF/Calib_DB_Reader/CHANGELOG.md
Keywords: Space Mission,BepiColombo,SIMBIO_SYS,Calibration Database,JUICE,JANUS
Classifier: License :: OSI Approved :: GNU General Public License v3 (GPLv3)
Requires-Python: <3.15,>=3.11
License-File: LICENSE
Requires-Dist: importlib-metadata
Requires-Dist: gitpython<4.0.0,>=3.1.45
Requires-Dist: pandas<3.0.0,>=2.3.3
Requires-Dist: pyyaml<7.0.0,>=6.0.3
Requires-Dist: numpy<3.0.0,>=2.3.4
Provides-Extra: docs
Requires-Dist: sphinx; extra == "docs"
Dynamic: license-file
